[
  {
    "Id": 58886819397637,
    "ConfigId": 58883053432837,
    "Json": "{\"Avatar\":\"https://img1.dotnet9.com/site/logo.png\",\"NikeName\":\"沙漠尽头的狼\",\"QQ\":\"632871194\",\"Github\":\"http://github.com/dotnet9/Dotnet9\",\"Gitee\":\"https://gitee.com/dotnet9/Dotnet9\",\"Motto\":\"时间如流水，只能流去不流回。\",\"About\":\"\"}",
    "Status": "0",
    "CreatedUserId": "1",
    "DeleteMark": "0",
    "CreatedTime": "2023-06-01"
  },
  {
    "Id": 60182392004613,
    "ConfigId": 52422632574981,
    "Json": "{\"Logo\":null,\"Favicon\":\"https://img1.dotnet9.com/site/logo.png\",\"IsRewards\":true,\"AliPay\":\"https://img1.dotnet9.com/pays/AliPay.jpg\",\"WxPay\":\"https://img1.dotnet9.com/pays/WeChatPay.jpg\",\"IsAllowMessage\":true,\"IsAllowComments\":true,\"Announcement\":\"新版本博客正式上线！！！\",\"SiteName\":\"沙漠尽头的狼\",\"Motto\":\"为遇一人而入红尘，人去我亦去，此生不留尘。 --魔道祖师\",\"RunTime\":\"2019-11-12 00:00:00\",\"VisitorNumbers\":536,\"Copyright\":\"© 2019~2023 https://dotnet9.com & 沙漠尽头的狼，由 .NET 8.0 强力驱动\",\"Description\":\"Dotnet9是一个热衷于互联网分享精神的网站\",\"Keyword\":\"Dotnet9,.NET Core,SqlSugar,开源\",\"Filing\":\"蜀ICP备19038256号-1\"}",
    "Status": "0",
    "CreatedUserId": "1",
    "DeleteMark": "0",
    "CreatedTime": "2023-06-01"
  },
  {
    "Id": 72581433774085,
    "ConfigId": 51073824051205,
    "Json": "{\"Password\":\"123456\",\"Times\":5,\"PasswordRule\":\"\",\"RuleMessage\":\"\",\"TokenExpired\":60,\"IsSso\":true,\"Logo\":null,\"Favicon\":null,\"AliPay\":null,\"WxPay\":null}",
    "Status": "0",
    "CreatedUserId": "1",
    "DeleteMark": "0",
    "CreatedTime": "2023-06-01"
  }
]
